wakepy/__init__.py
wakepy/__main__.py
wakepy/_version.py
wakepy/py.typed
wakepy/core/__init__.py
wakepy/core/activationresult.py
wakepy/core/constants.py
wakepy/core/dbus.py
wakepy/core/heartbeat.py
wakepy/core/method.py
wakepy/core/mode.py
wakepy/core/platform.py
wakepy/core/prioritization.py
wakepy/core/registry.py
wakepy/core/strenum.py
wakepy/dbus_adapters/__init__.py
wakepy/dbus_adapters/jeepney.py
wakepy/methods/__init__.py
wakepy/methods/_testing.py
wakepy/methods/freedesktop.py
wakepy/methods/gnome.py
wakepy/methods/macos.py
wakepy/methods/windows.py
wakepy/modes/__init__.py
wakepy/modes/keep.py
wakepy-0.10.2.post1.dist-info/LICENSE.txt
wakepy-0.10.2.post1.dist-info/METADATA
wakepy-0.10.2.post1.dist-info/WHEEL
wakepy-0.10.2.post1.dist-info/entry_points.txt
wakepy-0.10.2.post1.dist-info/top_level.txt
wakepy-0.10.2.post1.dist-info/RECORD
