Metadata-Version: 2.1
Name: wakepy
Version: 0.10.2.post1
Summary: wakelock / keep-awake / stay-awake
Author-email: Niko Föhr <fohrloop@gmail.com>
License: MIT License
Project-URL: Homepage, https://github.com/fohrloop/wakepy
Project-URL: Source Code, https://github.com/fohrloop/wakepy
Project-URL: Issue Tracker, https://github.com/fohrloop/wakepy/issues
Project-URL: Documentation, https://wakepy.readthedocs.io/
Project-URL: Changelog, https://wakepy.readthedocs.io/stable/changelog.html
Classifier: License :: OSI Approved :: MIT License
Classifier: Operating System :: MacOS
Classifier: Operating System :: Microsoft :: Windows
Classifier: Operating System :: POSIX
Classifier: Operating System :: POSIX :: Linux
Classifier: Operating System :: POSIX :: BSD
Classifier: Operating System :: POSIX :: BSD :: OpenBSD
Classifier: Operating System :: POSIX :: BSD :: FreeBSD
Classifier: Operating System :: POSIX :: BSD :: NetBSD
Classifier: Operating System :: POSIX :: Other
Classifier: Operating System :: Unix
Classifier: Intended Audience :: Developers
Classifier: Programming Language :: Python :: 3
Classifier: Programming Language :: Python :: 3.7
Classifier: Programming Language :: Python :: 3.8
Classifier: Programming Language :: Python :: 3.9
Classifier: Programming Language :: Python :: 3.10
Classifier: Programming Language :: Python :: 3.11
Classifier: Programming Language :: Python :: 3.12
Classifier: Programming Language :: Python :: 3.13
Classifier: Topic :: Utilities
Requires-Python: >=3.7
License-File: LICENSE.txt
Requires-Dist: jeepney>=0.7.1; platform_system == "Linux" or platform_system == "FreeBSD" or platform_system == "OpenBSD" or platform_system == "NetBSD" or platform_system == "DragonFly" or platform_system == "SunOS" or platform_system == "AIX" or platform_system == "Minix"
Requires-Dist: typing-extensions; python_version < "3.8.0"
